classification_model/VERSION
classification_model/__init__.py
classification_model/config.yml
classification_model/pipeline.py
classification_model/predict.py
classification_model/train_pipeline.py
classification_model/config/__init__.py
classification_model/config/core.py
classification_model/datasets/__init__.py
classification_model/datasets/test.csv
classification_model/datasets/train.csv
classification_model/processing/__init__.py
classification_model/processing/data_manager.py
classification_model/processing/validation.py
classification_model/trained_models/__init__.py
classification_model/trained_models/classification_model_output_v3.0.3.pkl
customer_churn_classification_model-3.0.3.dist-info/METADATA
customer_churn_classification_model-3.0.3.dist-info/WHEEL
customer_churn_classification_model-3.0.3.dist-info/top_level.txt
customer_churn_classification_model-3.0.3.dist-info/RECORD
